quick_qemu/LICENSE.txt
quick_qemu/__init__.py
quick_qemu/__main__.py
quick_qemu/quick_qemu/__init__.py
quick_qemu-0.5.1.dist-info/entry_points.txt
quick_qemu-0.5.1.dist-info/licenses/LICENSE
quick_qemu-0.5.1.dist-info/WHEEL
quick_qemu-0.5.1.dist-info/METADATA
quick_qemu-0.5.1.dist-info/RECORD
